[
  {
    "id": 1,
    "username": "jack",
    "email": "jack@jack.jack",
    "password": "hello",
    "age": 99,
    "profilePicture": ""
  },
  {
    "id": 2,
    "username": "john",
    "email": "john@john.john",
    "password": "yoyo",
    "age": 1,
    "profilePicture": "http://localhost:5000/06-01-2022-12-12-28-angela-merkel-photo-georg-wendt-afp-1632475157.jpeg"
  },
  {
    "age": "2",
    "email": "bobby@bobby.bobby",
    "password": "bobbybobby",
    "username": "bobby",
    "id": 3,
    "profilePicture": "http://localhost:5000/06-01-2022-12-32-51-angela.jpeg"
  }
]